setup.cfg
setup.py
gain/__init__.py
gain/item.py
gain/log.py
gain/parser.py
gain/request.py
gain/selector.py
gain/spider.py
gain.egg-info/PKG-INFO
gain.egg-info/SOURCES.txt
gain.egg-info/dependency_links.txt
gain.egg-info/not-zip-safe
gain.egg-info/requires.txt
gain.egg-info/top_level.txt
gain/result/__init__.py
gain/result/base.py
gain/result/file_result.py
gain/result/mysql_result.py