Metadata-Version: 1.1
Name: gain
Version: 0.1.4
Summary: Web crawling framework for everyone.
Home-page: https://github.com/gaojiuli/gain
Author: Gaojiuli
Author-email: gaojiuli@gmail.com
License: GNU GPL 3
Platform: UNKNOWN
Classifier: Development Status :: 5 - Production/Stable
Classifier: Intended Audience :: Developers
Classifier: License :: OSI Approved :: GNU General Public License (GPL)
Classifier: Programming Language :: Python :: 3.5
Classifier: Programming Language :: Python :: 3.6
